argus_ai/__init__.py
argus_ai-0.0.2.dist-info/licenses/LICENSE
argus_ai-0.0.2.dist-info/METADATA
argus_ai-0.0.2.dist-info/WHEEL
argus_ai-0.0.2.dist-info/top_level.txt
argus_ai-0.0.2.dist-info/RECORD
