Metadata-Version: 2.4
Name: argus-ai
Version: 0.0.2
Summary: The All-Seeing Orchestrator for Hierarchical Autonomous Agents
Author-email: Jashua Gupta <findjashua+github@gmail.com>
License: MIT
Project-URL: Homepage, https://github.com/findjashua/argus-ai
Classifier: Programming Language :: Python :: 3
Classifier: License :: OSI Approved :: MIT License
Classifier: Operating System :: OS Independent
Requires-Python: >=3.9
License-File: LICENSE
Requires-Dist: langgraph
Requires-Dist: pydantic
Dynamic: license-file
